pikvm_cli/__init__.py
pikvm_cli/__main__.py
pikvm_cli-1.1.0.dist-info/METADATA
pikvm_cli-1.1.0.dist-info/WHEEL
pikvm_cli-1.1.0.dist-info/entry_points.txt
pikvm_cli-1.1.0.dist-info/top_level.txt
pikvm_cli-1.1.0.dist-info/RECORD
