Metadata-Version: 2.1
Name: pikvm-cli
Version: 1.1.0
Summary: CLI tool for managing PIKVM device
Home-page: https://github.com/lysyi3m/pikvm-cli
Author: Emil Kashkevich
Author-email: emil.kashkevich@gmail.com
License: MIT
Classifier: License :: OSI Approved :: MIT License
Classifier: Programming Language :: Python :: 3
Requires-Dist: click>=8.1.7
Requires-Dist: requests>=2.32.3
